Workbook

Sheet CF
A2: Timeline | B2: 45231 | C2: 45261 | D2: 45292 | E2: 45323 | F2: 45352 | G2: 45383 | H2: 45413 | I2: 45444 | J2: 45474 | K2: 45505 | L2: 45536 | M2: 45566 | N2: 45597 | O2: 45627 | P2: 45658 | Q2: 45689 | R2: 45717 | S2: 45748 | T2: 45778 | U2: 45809 | V2: 45839 | W2: 45870 | X2: 45901 | Y2: 45931 | Z2: 45962 | AA2: 45992 | AB2: 46023 | AC2: 46054 | AD2: 46082
A3: Net cash flow
A4: INFLOWS
A5: Sales revenue | B5: =(Revenues!$B$9/12) -> 4.2029167e+12 | C5: =(Revenues!$B$9/12) -> 4.2029167e+12 | D5: =Revenues!$C$9/12 -> 0 | E5: =Revenues!$C$9/12 -> 0 | F5: =Revenues!$C$9/12 -> 0 | G5: =Revenues!$C$9/12 -> 0 | H5: =Revenues!$C$9/12 -> 0 | I5: =Revenues!$C$9/12 -> 0 | J5: =Revenues!$C$9/12 -> 0 | K5: =Revenues!$C$9/12 -> 0 | ... O5: =Revenues!$C$9/12 -> 0 | P5: =Revenues!$D$9/12 -> 0 | Q5: =Revenues!$D$9/12 -> 0 | R5: =Revenues!$D$9/12 -> 0 | S5: =Revenues!$D$9/12 -> 0 | T5: =Revenues!$D$9/12 -> 0 | U5: =Revenues!$D$9/12 -> 0 | V5: =Revenues!$D$9/12 -> 0 | W5: =Revenues!$D$9/12 -> 0 | ... AA5: =Revenues!$D$9/12 -> 0 | AB5: =Revenues!$E$9/12 -> 4837652 | AC5: =Revenues!$E$9/12 -> 4837652 | AD5: =Revenues!$E$9/12 -> 4837652
A6: Government subsidies / incentives
A7: Joint venture funding
A9: OUTFLOWS
A10: CAPEX
A11: Engineering | B11: ='Data from MS project'!E3 -> 1342464
A12: Purchase process | J12: ='Data from MS project'!E16 -> 2800 | K12: ='Data from MS project'!E18 -> 2240
A13: Equipment and manufacturing | K13: =SUM('Data from MS project'!#REF!+'Data from MS project'!#REF!+'Data from MS project'!#REF!+'Data from MS project'!#REF!+'Data from MS project'!#REF!+'Data from MS project'!#REF!+'Data from MS project'!#REF!+ 'Data from MS project'!#REF!+'Data from MS project'!#REF!+'Data from MS project'!#REF!+'Data from MS project'!#REF!+'Data from MS project'!#REF!+'Data from MS project'!#REF!) -> #REF! | N13: =SUM('Data from MS project'!E50+'Data from MS project'!E47+'Data from MS project'!E38) -> 871300 | O13: ='Data from MS project'!E56 -> 480 | P13: =SUM('Data from MS project'!E32+'Data from MS project'!E35+'Data from MS project'!E53) -> 11000550 | Q13: =SUM('Data from MS project'!E65+'Data from MS project'!E62+'Data from MS project'!E59+'Data from MS project'!E44+'Data from MS project'!E41) -> 4401170
A14: Transportation | Q14: ='Data from MS project'!#REF!+'Data from MS project'!#REF!+'Data from MS project'!#REF!+'Data from MS project'!#REF!+'Data from MS project'!#REF!+'Data from MS project'!#REF!+'Data from MS project'!#REF!+'Data from MS project'!#REF!+'Data from MS project'!#REF! -> #REF! | S14: ='Data from MS project'!E70+'Data from MS project'!#REF!+'Data from MS project'!#REF! -> #REF!
A15: Total CAPEX | B15: =SUM(B11:B14) -> 1342464 | C15: =SUM(C11:C14) -> 0 | D15: =SUM(D11:D14) -> 0 | E15: =SUM(E11:E14) -> 0 | F15: =SUM(F11:F14) -> 0 | G15: =SUM(G11:G14) -> 0 | H15: =SUM(H11:H14) -> 0 | I15: =SUM(I11:I14) -> 0 | ... AD15: =SUM(AD11:AD14) -> 0
A17: OPEX
A18: Overhead costs | B18: ='Price Calculations, Assumptions'!#REF!*30 -> #REF! | C18: ='Price Calculations, Assumptions'!#REF!*30 -> #REF! | D18: ='Price Calculations, Assumptions'!#REF!*30 -> #REF! | E18: ='Price Calculations, Assumptions'!#REF!*30 -> #REF! | F18: ='Price Calculations, Assumptions'!#REF!*30 -> #REF! | G18: ='Price Calculations, Assumptions'!#REF!*30 -> #REF! | H18: ='Price Calculations, Assumptions'!#REF!*30 -> #REF! | I18: ='Price Calculations, Assumptions'!#REF!*30 -> #REF! | ... AD18: ='Price Calculations, Assumptions'!#REF!*30 -> #REF!
A19: Production line setup costs | B19: =SUM(B20:B31) -> 0 | C19: =SUM(C20:C31) -> 0 | D19: =SUM(D20:D31) -> 0 | E19: =SUM(E20:E31) -> 0 | F19: =SUM(F20:F31) -> 0 | G19: =SUM(G20:G31) -> 0 | H19: =SUM(H20:H31) -> 0 | I19: =SUM(I20:I31) -> 0 | ... AD19: =SUM(AD20:AD31) -> 24533.333
A20: OP.10 | U20: ='Data from MS project'!$E$95/5 -> 74160 | V20: ='Data from MS project'!$E$95/5 -> 74160 | W20: ='Data from MS project'!$E$95/5 -> 74160 | X20: ='Data from MS project'!$E$95/5 -> 74160 | Y20: ='Data from MS project'!$E$95/5 -> 74160
A21: OP.20 | T21: ='Data from MS project'!$E$104/5 -> 74160 | U21: ='Data from MS project'!$E$104/5 -> 74160 | V21: ='Data from MS project'!$E$104/5 -> 74160 | W21: ='Data from MS project'!$E$104/5 -> 74160 | X21: ='Data from MS project'!$E$104/5 -> 74160
A22: OP.30 | U22: ='Data from MS project'!$E$109/3 -> 147000 | V22: ='Data from MS project'!$E$109/3 -> 147000 | W22: ='Data from MS project'!$E$109/3 -> 147000
A23: OP.40 | U23: ='Data from MS project'!$E$118/5 -> 74160 | V23: ='Data from MS project'!$E$118/5 -> 74160 | W23: ='Data from MS project'!$E$118/5 -> 74160 | X23: ='Data from MS project'!$E$118/5 -> 74160 | Y23: ='Data from MS project'!$E$118/5 -> 74160
A24: OP.50 | V24: ='Data from MS project'!$E$127/5 -> 74160 | W24: ='Data from MS project'!$E$127/5 -> 74160 | X24: ='Data from MS project'!$E$127/5 -> 74160 | Y24: ='Data from MS project'!$E$127/5 -> 74160 | Z24: ='Data from MS project'!$E$127/5 -> 74160
A25: OP.60 | T25: ='Data from MS project'!$E$140/5 -> 74160 | U25: ='Data from MS project'!$E$140/5 -> 74160 | V25: ='Data from MS project'!$E$140/5 -> 74160 | W25: ='Data from MS project'!$E$140/5 -> 74160 | X25: ='Data from MS project'!$E$140/5 -> 74160
A26: OP.70 | T26: ='Data from MS project'!$E$145/3 -> 147000 | U26: ='Data from MS project'!$E$145/3 -> 147000 | V26: ='Data from MS project'!$E$145/3 -> 147000
A27: OP.80 | W27: ='Data from MS project'!$E$150/3 -> 147000 | X27: ='Data from MS project'!$E$150/3 -> 147000 | Y27: ='Data from MS project'!$E$150/3 -> 147000
A28: OP.90 | X28: ='Data from MS project'!$E$159/5 -> 74160 | Y28: ='Data from MS project'!$E$159/5 -> 74160 | Z28: ='Data from MS project'!$E$159/5 -> 74160 | AA28: ='Data from MS project'!$E$159/5 -> 74160 | AB28: ='Data from MS project'!$E$159/5 -> 74160
A29: OP.100 | Y29: ='Data from MS project'!$E$172/3 -> 147000 | Z29: ='Data from MS project'!$E$172/3 -> 147000 | AA29: ='Data from MS project'!$E$172/3 -> 147000
A30: OP.110 | X30: ='Data from MS project'!$E$177/5 -> 74160 | Y30: ='Data from MS project'!$E$177/5 -> 74160 | Z30: ='Data from MS project'!$E$177/5 -> 74160 | AA30: ='Data from MS project'!$E$177/5 -> 74160 | AB30: ='Data from MS project'!$E$177/5 -> 74160
A31: Final Line Testing | AB31: ='Data from MS project'!$E$182/3 -> 24533.333 | AC31: ='Data from MS project'!$E$182/3 -> 24533.333 | AD31: ='Data from MS project'!$E$182/3 -> 24533.333
A32: Contingency fund
A33: Total OPEX
A35: FV CF
A36: DCF
A37: NPV
A39: PV

Sheet Historical Financials
B1: Economics (M€) | G1: Cash flow (M€) | L1: Indicators
C2: 2021 | D2: 2022 | E2: Change | H2: 2022 | I2: 2021 | J2: Change | M2: 2022 | N2: 2021 | O2: Change
B3: Sales | C3: 394 | D3: 326 | E3: =-(C3-D3)/C3 -> -0.17258883 | G3: Operating cash-flow | L3: Return on Invested Capital
B4: Cost of goods sold | C4: 340 | D4: 282 | E4: =-(C4-D4)/C4 -> -0.17058824 | G4: Net income | H4: 68 | I4: 163 | J4: =-(I4-H4)/I4 -> -0.58282209 | L4: ROI | M4: 4,70% | N4: 10,10% | O4: -53%
B5: Material | C5: 246 | D5: 197 | E5: =-(C5-D5)/C5 -> -0.19918699 | G5: Items not involving current cash flows | H5: 206 | I5: 198 | J5: =-(I5-H5)/I5 -> 0.04040404 | L5: Return on Equity
B6: Direct labor | C6: 28 | D6: 25 | E6: =-(C6-D6)/C6 -> -0.10714286 | G6: Changes in operating assets and liabilities | H6: 54 | I6: 35 | J6: =-(I6-H6)/I6 -> 0.54285714 | L6: ROE | M6: 7,00% | N6: 15,50% | O6: -55%
B7: Overhead | C7: 66 | D7: 60 | E7: =-(C7-D7)/C7 -> -0.090909091 | G7: Cash provided from operations | H7: =SUM(H4:H6) -> 328 | I7: =SUM(I4:I6) -> 396 | J7: =-(I7-H7)/I7 -> -0.17171717
B8: S.G.A. | C8: 16 | D8: 15 | E8: =-(C8-D8)/C8 -> -0.0625 | G8: Fixed asset additions | H8: -115 | I8: -144 | J8: =-(I8-H8)/I8 -> -0.20138889
B9: Selling | C9: 9 | D9: 8 | E9: =-(C9-D9)/C9 -> -0.11111111 | G9: Increase in investments, other tangible, and intangible assets | H9: -33 | I9: -38 | J9: =-(I9-H9)/I9 -> -0.13157895
B10: General | C10: 5 | D10: 5 | E10: 0% | G10: Cash used for investing | H10: =SUM(H8:H9) -> -148 | I10: =SUM(I8:I9) -> -182 | J10: =-(I10-H10)/I10 -> -0.18681319
B11: Administrative | C11: 2 | D11: 2 | E11: 0% | G11: Net Cash-flow | H11: =H7+H10 -> 180 | I11: =I7+I10 -> 214 | J11: =-(I11-H11)/I11 -> -0.1588785
B12: EBITDA | C12: 38 | D12: 29 | E12: =-(C12-D12)/C12 -> -0.23684211
B13: % of Sales | C13: =C12/C3 -> 0.096446701 | D13: =D12/D3 -> 0.088957055

Sheet Price Calculations, Assumptions
A4: Project 1 | D4: Subtotal | E4: Total | I4: Assumptions
A5: Direct costs | B5: Start date | C5: Finish date | I5: Debt ratio | J5: 0.8
A6: Phases | I6: Equity ratio | J6: 0.2
A7: Erection phase & Final line testing | B7: ='Data from MS project'!C94 -> 45658 | C7: ='Data from MS project'!D182 -> 46069 | D7: 607030 | I7: Joint Venture Magnus | J7: 0.49
A8: Total | E8: =SUM(D7:D7) -> 607030 | I8: Joint Venture GPC | J8: 0.51
A9: Indirect costs
A10: Engineering phase | B10: ='Data from MS project'!C3 -> 45306 | C10: ='Data from MS project'!D3 -> 45478 | D10: ='Data from MS project'!E3 -> 1342464 | I10: corporate tax rate | J10: 0.34
A11: Purchase phase | B11: ='Data from MS project'!C15 -> 45467 | C11: ='Data from MS project'!D15 -> 45488 | D11: ='Data from MS project'!E15 -> 5670
A12: Manufacturing phase | B12: ='Data from MS project'!C29 -> 45485 | C12: ='Data from MS project'!D29 -> 45672 | D12: ='Data from MS project'!E29 -> 18686638 | I12: Total CAPEX | J12: =SUM('Cash flow'!C34:D34) -> 22796937
A13: Transportation phase | B13: ='Data from MS project'!C66 -> 45485 | C13: ='Data from MS project'!D66 -> 45671 | D13: ='Data from MS project'!E66 -> 112550 | I13: Equity Project 1 | J13: =J6*J12 -> 4559387.3
A14: Total | E14: =SUM(D10:D13) -> 20147322 | I14: Debt Project 1 | J14: =J5*J12 -> 18237549
A15: Manufacturing line | B15: ='Data from MS project'!C2 -> Mon 24-01-15 | C15: ='Data from MS project'!D2 -> Tue 26-07-07 | E15: =SUM(D7:D9) -> 607030
A18: Project 2 | D18: Subtotal | E18: Total | J18: Duration projects (days)
A19: Direct costs | B19: Start date | C19: Finish date | L19: Total
A20: Phases | I20: Total | J20: 45232 | K20: 46182
A21: ERP Implementation | B21: ='Data from MS project'!M3 -> 45672 | C21: ='Data from MS project'!N3 -> 46206 | D21: ='Data from MS project'!O3 -> 248120
A22: Meeting with stakeholders | B22: ='Data from MS project'!M47 -> 46206 | C22: ='Data from MS project'!N47 -> 46209 | D22: ='Data from MS project'!O47 -> 2000
A23: Total | B23: ='Data from MS project'!M2 -> 45672 | C23: ='Data from MS project'!N2 -> 46209 | E23: =SUM(D21:D22) -> 250120 | I23: Year 2023 | J23: 45232 | K23: 45291 | L23: =_xlfn.DAYS(K23,J23) -> 59
I24: Year 2026 | J24: 46023 | K24: 46182 | L24: =_xlfn.DAYS(K24,J24) -> 159
A26: Price calculation | D26: Subtotal | E26: Total
A27: Direct costs | B27: Start date | C27: Finish date
A28: Project 1 | B28: =B15 -> Mon 24-01-15 | C28: =C15 -> Tue 26-07-07 | D28: =E8 -> 607030
A29: Project 2 | B29: =B23 -> 45672 | C29: =C23 -> 46209 | D29: =E23 -> 250120
A30: Total | B30: =B28 -> Mon 24-01-15 | C30: =C29 -> 46209 | E30: =SUM(D28:D29) -> 857150
A31: Indirect costs
A32: Total | E32: =E14 -> 20147322
A33: Overhead costs
A34: Daily overhead costs | D34: =(E32/10)/365 -> 5519.8142
A35: Project duration | B35: 45306 | C35: 46210 | D35: 646.45
A36: Overhead costs | E36: =D35*D34 -> 3568283.9
A37: Contingency
A38: Calculated CO
A39: Interest on capital
A40: Calculated IoC
A41: Total project cost
A42: Profit rate
A43: X
A46: Depreciation
A47: Initial value of the machines | B47: 18683200
A48: Residual value is 30% | B48: =B47*0.3 -> 5604960
A49: Depreciation | B49: =(B47-B48)/10 -> 1307824

Sheet Data from MS project
A1: WBS | B1: Task Name | C1: Start | D1: Finish | E1: Total Cost | F1: Baseline | G1: Variance | H1: Actual | K1: WBS | L1: Task Name | M1: Start | N1: Finish | O1: Cost
A2: 1 | B2: Project | C2: Mon 24-01-15 | D2: Tue 26-07-07 | E2: =E3+E6+E15+E29+E94+E182+E81 -> 24611812 | F2: 0 | G2: 4579375 | H2: 0 | K2: 1.2 | L2: Project2 | M2: 45672 | N2: 46209 | O2: 207682
A3: 1.1 | B3: ENGINEERING PHASE | C3: 45306 | D3: 45478 | E3: =SUM(E4:E5) -> 1342464 | F3: 0 | G3: 632320 | H3: 0 | K3: 1.2.1 | L3: ERP Implementation | M3: 45672 | N3: 46206 | O3: 248120
A4: 1.1.1 | B4: Detailed Engineering - Process | C4: 45306 | D4: 45478 | E4: 918528 | F4: 0 | G4: 432640 | H4: 0 | K4: 1.2.1.1 | L4: Prepare | M4: 45672 | N4: 45728 | O4: 56256
A5: 1.1.1.1 | B5: Detailed Engineering - Layout | C5: 45306 | D5: 45467 | E5: 423936 | F5: 0 | G5: 199680 | H5: 0 | K5: 1.2.1.1.1 | L5: Plan the meeting and revise requirements | M5: 45672 | N5: 45684 | O5: 15040
A6: 1.1.1.2 | B6: CIVIL WORKS REFURBISHMENT ERECTION PHASE | C6: 45478 | D6: 45721 | E6: =SUM(E7:E14) -> 840 | F6: 0 | G6: 0 | H6: 0 | K6: 1.2.1.1.2 | L6: Develop projet plan | M6: 45684 | N6: 45694 | O6: 6464
A7: 1.1.2 | B7: Design Civil Works | C7: 45478 | D7: 45555 | E7: 0 | F7: 0 | G7: 0 | H7: 0 | K7: 1.2.1.1.2.1 | L7: Develop Project Charter | M7: 45684 | N7: 45686 | O7: 1616
A8: 1.1.2.1 | B8: Permits and Authorizations | C8: 45520 | D8: 45562 | E8: 0 | F8: 0 | G8: 0 | H8: 0 | K8: 1.2.1.1.2.2 | L8: Define project and quality management processes | M8: 45686 | N8: 45688 | O8: 1616
A9: 1.1.2.2 | B9: Site Installation | C9: 45541 | D9: 45562 | E9: 0 | F9: 0 | G9: 0 | H9: 0 | K9: 1.2.1.1.2.3 | L9: Create Master Plan | M9: 45688 | N9: 45692 | O9: 1616
A10: 1.1.2.3 | B10: Excavations & Foundations | C10: 45562 | D10: 45604 | E10: 0 | F10: 0 | G10: 0 | H10: 0 | K10: 1.2.1.1.2.4 | L10: Craft detailed work plan | M10: 45692 | N10: 45694 | O10: 1616
A11: 1.1.2.4 | B11: Structural Improvement | C11: 45583 | D11: 45632 | E11: 0 | F11: 0 | G11: 0 | H11: 0 | K11: 1.2.1.1.3 | L11: Validate and prioritize requirements | M11: 45694 | N11: 45706 | O11: 6464
A12: 1.1.2.5 | B12: Industrial Flooring | C12: 45632 | D12: 45681 | E12: 0 | F12: 0 | G12: 0 | H12: 0 | K12: 1.2.1.1.4 | L12: Establish governance and communicating strategy | M12: 45706 | N12: 45716 | O12: 16000
A13: 1.1.2.6 | B13: Finishes | C13: 45667 | D13: 45721 | E13: 0 | F13: 0 | G13: 0 | H13: 0 | K13: 1.2.1.1.4.1 | L13: Establish organizational structure | M13: 45706 | N13: 45709 | O13: 6000
A14: 1.1.2.7 | B14: Civil work final meeting | C14: 45721 | D14: 45722 | E14: 840 | F14: 0 | G14: 2520 | H14: 0 | K14: 1.2.1.1.4.2 | L14: Devise project tool strategy | M14: 45709 | N14: 45714 | O14: 6000
A15: 1.1.2.8 | B15: PURCHASE PROCESS (to repeat for each equipment type) | C15: 45467 | D15: 45488 | E15: =SUM(E16:E19) -> 5670 | F15: 0 | G15: 1400 | H15: 0 | K15: 1.2.1.1.4.3 | L15: Assign resources to tasks | M15: 45714 | N15: 45716 | O15: 4000
A16: 1.1.3 | B16: Request for proposals | C16: 45467 | D16: 45469 | E16: 2800 | F16: 0 | G16: 0 | H16: 0 | K16: 1.2.1.1.5 | L16: Hire resources | M16: 45716 | N16: 45728 | O16: 12288
A17: 1.1.3.1 | B17: Waiting period | C17: 45469 | D17: 45483 | E17: 0 | F17: 0 | G17: 1120 | H17: 0 | K17: 1.2.1.2 | L17: Explore | M17: 45728 | N17: 45812 | O17: 48080
A18: 1.1.3.2 | B18: Competitive proposal analysis | C18: 45483 | D18: 45485 | E18: 2240 | F18: 0 | G18: 0 | H18: 0 | K18: 1.2.1.2.1 | L18: Perform AS IS analysis | M18: 45728 | N18: 45742 | O18: 3040
A19: 1.1.3.3 | B19: Orders | C19: 45485 | D19: 45488 | E19: =SUM(E20:E28) -> 630 | F19: 0 | G19: 0 | H19: 0 | K19: 1.2.1.2.2 | L19: Perform FIT GAP analysis | M19: 45742 | N19: 45756 | O19: 16040
A20: 1.1.3.4 | B20: CNC Machine (Double and Single spindle) order | C20: 45485 | D20: 45485 | E20: 70 | F20: 0 | G20: 0 | H20: 0 | K20: 1.2.1.2.3 | L20: Perform TO BE analysis | M20: 45756 | N20: 45770 | O20: 3040
A21: 1.1.3.4.1 | B21: Drilling Machine order | C21: 45485 | D21: 45485 | E21: 70 | F21: 0 | G21: 0 | H21: 0 | K21: 1.2.1.2.4 | L21: Develop functional specification and realization plan | M21: 45770 | N21: 45784 | O21: 6480
A22: 1.1.3.4.2 | B22: Conveyors order (Powered and Overhead) | C22: 45485 | D22: 45485 | E22: 70 | F22: 0 | G22: 0 | H22: 0 | K22: 1.2.1.2.5 | L22: Develop security, privacy and controls approach | M22: 45784 | N22: 45798 | O22: 3440
A23: 1.1.3.4.3 | B23: Washing station (Final and Intermidiate) order | C23: 45485 | D23: 45485 | E23: 70 | F23: 0 | G23: 0 | H23: 0 | K23: 1.2.1.2.6 | L23: Develop Business Process Blueprints | M23: 45798 | N23: 45812 | O23: 16040
A24: 1.1.3.4.4 | B24: Assembly Station order | C24: 45485 | D24: 45485 | E24: 70 | F24: 0 | G24: 0 | H24: 0 | K24: 1.2.1.3 | L24: Build | M24: 45812 | N24: 45952 | O24: 56880
A25: 1.1.3.4.5 | B25: Gantry Loader order | C25: 45485 | D25: 45485 | E25: 70 | F25: 0 | G25: 0 | H25: 0 | K25: 1.2.1.3.1 | L25: Develop technical specifications | M25: 45812 | N25: 45840 | O25: 16320
A26: 1.1.3.4.6 | B26: Rotating Table | C26: 45485 | D26: 45485 | E26: 70 | F26: 0 | G26: 0 | H26: 0 | K26: 1.2.1.3.2 | L26: Develop configuration and code | M26: 45840 | N26: 45868 | O26: 8080
A27: 1.1.3.4.7 | B27: Lift/Lower Components | C27: 45485 | D27: 45485 | E27: 70 | F27: 0 | G27: 0 | H27: 0 | K27: 1.2.1.3.3 | L27: Perform unit test | M27: 45868 | N27: 45896 | O27: 8080
A28: 1.1.3.4.8 | B28: Manipulator | C28: 45485 | D28: 45488 | E28: 70 | K28: 1.2.1.3.4 | L28: Develop learning documentation | M28: 45896 | N28: 45924 | O28: 8080
A29: 1.4 | B29: EQUIPMENT MANUFACTURING PHASE (values for each unit of equipment) | C29: 45485 | D29: 45672 | E29: =E30+E34+E38+E42+E46+E50+E54+E58+E62+E66+E70+E74+E78 -> 18686638 | K29: 1.2.1.3.5 | L29: Develop Go/No Go criteria and deployment plan | M29: 45924 | N29: 45952 | O29: 16320
A30: 1.4.1 | B30: Single Spindle machine | C30: 45485 | D30: 45642 | E30: 1020550 | K30: 1.2.1.4 | L30: Test | M30: 46070 | N30: 46115 | O30: 19224
A31: 1.4.1.1 | B31: Single Spindle Machine | C31: 45485 | D31: 45639 | E31: 1020000 | K31: 1.2.1.4.1 | L31: Conduct integration test | M31: 46070 | N31: 46078 | O31: 2424
A32: 1.4.1.2 | B32: Technical requiremets check | C32: 45639 | D32: 45642 | E32: 480 | K32: 1.2.1.4.2 | L32: Conduct mock data conversion | M32: 46078 | N32: 46086 | O32: 2424
A33: 1.4.1.3 | B33: Payment | C33: 45642 | D33: 45642 | E33: 70 | K33: 1.2.1.4.3 | L33: Develop a transition plan | M33: 46086 | N33: 46091 | O33: 4992
A34: 1.4.2 | B34: Double Spindle Machine | C34: 45485 | D34: 45642 | E34: 11000550 | K34: 1.2.1.4.4 | L34: Prepare for user acceptance test | M34: 46091 | N34: 46107 | O34: 3648
A35: 1.4.2.1 | B35: Double Spindle machine | C35: 45485 | D35: 45639 | E35: 11000000 | K35: 1.2.1.4.5 | L35: Conduct acceptance test | M35: 46107 | N35: 46115 | O35: 5736
A36: 1.4.2.2 | B36: Technical requiremets check | C36: 45639 | D36: 45642 | E36: 480 | K36: 1.2.1.5 | L36: Deploy | M36: 46115 | N36: 46150 | O36: 11178
A37: 1.4.2.3 | B37: Payment | C37: 45642 | D37: 45642 | E37: 70 | K37: 1.2.1.5.1 | L37: Meeting to start project 3 | M37: 46115 | N37: 46118 | O37: 1906
A38: 1.4.3 | B38: Drilling machine | C38: 45485 | D38: 45580 | E38: 270550 | K38: 1.2.1.5.2 | L38: Deploy learning to end-users | M38: 46118 | N38: 46132 | O38: 600
A39: 1.4.3.1 | B39: Drilling machine | C39: 45485 | D39: 45579 | E39: 270000 | K39: 1.2.1.5.3 | L39: Conduct deployment Go/No Go decision set | M39: 46132 | N39: 46139 | O39: 2060
A40: 1.4.3.2 | B40: Technical requiremets check | C40: 45579 | D40: 45580 | E40: 480 | K40: 1.2.1.5.4 | L40: Execute production deployment | M40: 46139 | N40: 46143 | O40: 3072
A41: 1.4.3.3 | B41: Payment | C41: 45580 | D41: 45580 | E41: 70 | K41: 1.2.1.5.5 | L41: Execute final data migration | M41: 46143 | N41: 46150 | O41: 3540
... A47: 1.4.5.1 | B47: Overhead Conveyors | C47: 45485 | D47: 45667 | E47: 70200 | K47: 1.2.2 | L47: Meeting with Stakeholders for project 2 closure | M47: 46206 | N47: 46209 | O47: 2000
A48: 1.4.5.2 | B48: Technical requiremets check | C48: 45667 | D48: 45670 | E48: 480
A49: 1.4.5.3 | B49: Payment | C49: 45670 | D49: 45670 | E49: 70
A50: 1.4.6 | B50: Intermidiate Washing stations | C50: 45485 | D50: 45586 | E50: 530550
A51: 1.4.6.1 | B51: Intermidiate Washing stations | C51: 45485 | D51: 45583 | E51: 530000
A52: 1.4.6.2 | B52: Technical requiremets check | C52: 45583 | D52: 45586 | E52: 480
A53: 1.4.6.3 | B53: Payment | C53: 45586 | D53: 45586 | E53: 70
A54: 1.4.7 | B54: Final Washing station | C54: 45485 | D54: 45586 | E54: 970550
A55: 1.4.7.1 | B55: Final Washing station | C55: 45485 | D55: 45583 | E55: 970000
A56: 1.4.7.2 | B56: Technical requiremets check | C56: 45583 | D56: 45586 | E56: 480
A57: 1.4.7.3 | B57: Payment | C57: 45586 | D57: 45586 | E57: 70
A58: 1.4.8 | B58: Assembly station | C58: 45485 | D58: 45629 | E58: 2200550
A59: 1.4.8.1 | B59: Assembly station | C59: 45485 | D59: 45625 | E59: 2200000
... A64: 1.4.9.2 | B64: Technical requiremets check | C64: 45618 | D64: 45621 | E64: 480
A65: 1.4.9.3 | B65: Payment | C65: 45621 | D65: 45622 | E65: 70 | F65: 0 | G65: 253675 | H65: 0
A66: 1.4.10 | B66: Rotating Table | C66: 45485 | D66: 45671 | E66: 112550 | F66: 0 | G66: 62500 | H66: 0
A67: 1.4.10.1 | B67: Rotating Table | C67: 45485 | D67: 45667 | E67: 112000 | F67: 0 | G67: 62500 | H67: 0
A68: 1.4.10.2 | B68: Technical requiremets check | C68: 45667 | D68: 45670 | E68: 480 | F68: 0 | G68: 55000 | H68: 0
A69: 1.4.10.3 | B69: Payment | C69: 45670 | D69: 45671 | E69: 70 | F69: 0 | G69: 7500 | H69: 0
A70: 1.4.11 | B70: Lift/Lower Components | C70: 45485 | D70: 45671 | E70: 32950 | F70: 0 | G70: 975 | H70: 0
A71: 1.4.11.1 | B71: Lift/Lower Components | C71: 45485 | D71: 45667 | E71: 32400 | F71: 0 | G71: 1000 | H71: 0
A72: 1.4.11.2 | B72: Technical requiremets check | C72: 45667 | D72: 45670 | E72: 480 | F72: 0 | G72: 31250 | H72: 0
A73: 1.4.11.3 | B73: Payment | C73: 45670 | D73: 45671 | E73: 70 | F73: 0 | G73: 2450 | H73: 0
A74: 1.4.12 | B74: Manipulator | C74: 45488 | D74: 45671 | E74: 22550 | F74: 0 | G74: 1000 | H74: 0
A75: 1.4.12.1 | B75: Manipulator | C75: 45488 | D75: 45670 | E75: 22000 | F75: 0 | G75: 14000 | H75: 0
A76: 1.4.12.2 | B76: Technical requiremets check | C76: 45670 | D76: 45671 | E76: 480 | F76: 0 | G76: 14000 | H76: 0
A77: 1.4.12.3 | B77: Payment | C77: 45671 | D77: 45671 | E77: 70 | F77: 0 | G77: 1500 | H77: 0
A78: 1.1.4.13 | B78: Meeting to start project 2 & 3 | C78: 45671 | D78: 45672 | E78: 3438
A79: 1.1.4.13.1 | B79: Meeting to start project 2 | C79: 45671 | D79: 45671 | E79: 1280
A80: 1.1.4.13.2 | B80: Meeting to start project 3 | C80: 45671 | D80: 45672 | E80: 2158
A81: 1.1.5 | B81: TRANSPORTATION PHASE (from the contractor to the owner's construction site) | C81: 45580 | D81: 45755 | E81: 143000
A82: 1.1.5.1 | B82: Single Spindle Machine | C82: 45642 | D82: 45726 | E82: 10000
A83: 1.1.5.2 | B83: Double Spindle Machine | C83: 45642 | D83: 45726 | E83: 55000
A84: 1.1.5.3 | B84: Drilling Machine | C84: 45580 | D84: 45664 | E84: 5000
A85: 1.1.5.4 | B85: Powered Conveyors | C85: 45670 | D85: 45691 | E85: 7500
A86: 1.1.5.5 | B86: Overhead Conveyors | C86: 45670 | D86: 45691 | E86: 1500
A87: 1.1.5.6 | B87: Manipulator | C87: 45671 | D87: 45755 | E87: 5000
A88: 1.1.5.7 | B88: Gantry Loader | C88: 45622 | D88: 45706 | E88: 35000
A89: 1.1.5.8 | B89: Rotating table | C89: 45671 | D89: 45734 | E89: 3500
... A93: 1.1.5.12 | B93: Assembly station | C93: 45637 | D93: 45658 | E93: 1500
A94: 1.6 | B94: ON SITE ERECTION PHASE | C94: 45658 | D94: 46042 | E94: 4359600 | F94: 0 | G94: 123600 | H94: 0
A95: 1.6.1 | B95: OP.10 | C95: 45726 | D95: 45852 | E95: 370800 | F95: 0 | G95: 61800 | H95: 0
A96: 1.6.1.1 | B96: Single-spindle cnc machine 1 | C96: 45726 | D96: 45789 | E96: 185400 | F96: 0 | G96: 23400 | H96: 0
A97: 1.6.1.1.1 | B97: Installation | C97: 45726 | D97: 45789 | E97: 70200 | F97: 0 | G97: 12800 | H97: 0
A98: 1.6.1.1.2 | B98: Electrical&IT Connections | C98: 45726 | D98: 45733 | E98: 38400 | F98: 0 | G98: 25600 | H98: 0
A99: 1.6.1.1.3 | B99: Final Assembly | C99: 45733 | D99: 45747 | E99: 76800 | F99: 0 | G99: 61800 | H99: 0
A100: 1.6.1.2 | B100: Single-spindle cnc machine 2 | C100: 45789 | D100: 45852 | E100: 185400 | F100: 0 | G100: 23400 | H100: 0
A101: 1.6.1.2.1 | B101: Installation | C101: 45789 | D101: 45852 | E101: 70200 | F101: 0 | G101: 12800 | H101: 0
A102: 1.6.1.2.2 | B102: Electrical&IT Connections | C102: 45789 | D102: 45796 | E102: 38400 | F102: 0 | G102: 25600 | H102: 0
A103: 1.6.1.2.3 | B103: Final Assembly | C103: 45796 | D103: 45810 | E103: 76800 | F103: 0 | G103: 123600 | H103: 0
A104: 1.6.2 | B104: OP.20 | C104: 45664 | D104: 45790 | E104: 370800 | F104: 0 | G104: 123600 | H104: 0
A105: 1.6.2.1 | B105: Drilling machine | C105: 45664 | D105: 45790 | E105: 370800 | F105: 0 | G105: 46800 | H105: 0
... A182: 1.7 | B182: FINAL LINE TESTING | C182: 46042 | D182: 46069 | E182: 73600 | F182: 0 | G182: 147200 | H182: 0
A183: 1.7.1 | B183: Testing | C183: 46042 | D183: 46070 | E183: 73600

Sheet CF (2)
A2: Timeline | B2: 45231 | C2: 45261 | D2: 45292 | E2: 45323 | F2: 45352 | G2: 45383 | H2: 45413 | I2: 45444 | J2: 45474 | K2: 45505 | L2: 45536 | M2: 45566 | N2: 45597 | O2: 45627 | P2: 45658 | Q2: 45689 | R2: 45717 | S2: 45748 | T2: 45778 | U2: 45809 | V2: 45839 | W2: 45870 | X2: 45901 | Y2: 45931 | Z2: 45962 | AA2: 45992 | AB2: 46023 | AC2: 46054 | AD2: 46082
A3: Net cash flow
A4: INFLOWS
A5: Sales revenue | B5: =(Revenues!$B$9/12) -> 4.2029167e+12 | C5: =(Revenues!$B$9/12) -> 4.2029167e+12 | D5: =Revenues!$C$9/12 -> 0 | E5: =Revenues!$C$9/12 -> 0 | F5: =Revenues!$C$9/12 -> 0 | G5: =Revenues!$C$9/12 -> 0 | H5: =Revenues!$C$9/12 -> 0 | I5: =Revenues!$C$9/12 -> 0 | J5: =Revenues!$C$9/12 -> 0 | K5: =Revenues!$C$9/12 -> 0 | ... O5: =Revenues!$C$9/12 -> 0 | P5: =Revenues!$D$9/12 -> 0 | Q5: =Revenues!$D$9/12 -> 0 | R5: =Revenues!$D$9/12 -> 0 | S5: =Revenues!$D$9/12 -> 0 | T5: =Revenues!$D$9/12 -> 0 | U5: =Revenues!$D$9/12 -> 0 | V5: =Revenues!$D$9/12 -> 0 | W5: =Revenues!$D$9/12 -> 0 | ... AA5: =Revenues!$D$9/12 -> 0 | AB5: =Revenues!$E$9/12 -> 4837652 | AC5: =Revenues!$E$9/12 -> 4837652 | AD5: =Revenues!$E$9/12 -> 4837652
A6: Government subsidies / incentives
A7: Joint venture funding
A9: OUTFLOWS
A10: OPEX
A11: Overhead costs | B11: ='Price Calculations, Assumptions'!#REF!*30 -> #REF! | C11: ='Price Calculations, Assumptions'!#REF!*30 -> #REF! | D11: ='Price Calculations, Assumptions'!#REF!*30 -> #REF! | E11: ='Price Calculations, Assumptions'!#REF!*30 -> #REF! | F11: ='Price Calculations, Assumptions'!#REF!*30 -> #REF! | G11: ='Price Calculations, Assumptions'!#REF!*30 -> #REF! | H11: ='Price Calculations, Assumptions'!#REF!*30 -> #REF! | I11: ='Price Calculations, Assumptions'!#REF!*30 -> #REF! | ... AD11: ='Price Calculations, Assumptions'!#REF!*30 -> #REF!
A12: Production line setup costs | B12: =SUM(B13:B24) -> 0 | C12: =SUM(C13:C24) -> 0 | D12: =SUM(D13:D24) -> 0 | E12: =SUM(E13:E24) -> 0 | F12: =SUM(F13:F24) -> 0 | G12: =SUM(G13:G24) -> 0 | H12: =SUM(H13:H24) -> 0 | I12: =SUM(I13:I24) -> 0 | ... AD12: =SUM(AD13:AD24) -> 24533.333
A13: OP.10 | U13: ='Data from MS project'!$E$95/5 -> 74160 | V13: ='Data from MS project'!$E$95/5 -> 74160 | W13: ='Data from MS project'!$E$95/5 -> 74160 | X13: ='Data from MS project'!$E$95/5 -> 74160 | Y13: ='Data from MS project'!$E$95/5 -> 74160
A14: OP.20 | T14: ='Data from MS project'!$E$104/5 -> 74160 | U14: ='Data from MS project'!$E$104/5 -> 74160 | V14: ='Data from MS project'!$E$104/5 -> 74160 | W14: ='Data from MS project'!$E$104/5 -> 74160 | X14: ='Data from MS project'!$E$104/5 -> 74160
A15: OP.30 | U15: ='Data from MS project'!$E$109/3 -> 147000 | V15: ='Data from MS project'!$E$109/3 -> 147000 | W15: ='Data from MS project'!$E$109/3 -> 147000
A16: OP.40 | U16: ='Data from MS project'!$E$118/5 -> 74160 | V16: ='Data from MS project'!$E$118/5 -> 74160 | W16: ='Data from MS project'!$E$118/5 -> 74160 | X16: ='Data from MS project'!$E$118/5 -> 74160 | Y16: ='Data from MS project'!$E$118/5 -> 74160
A17: OP.50 | V17: ='Data from MS project'!$E$127/5 -> 74160 | W17: ='Data from MS project'!$E$127/5 -> 74160 | X17: ='Data from MS project'!$E$127/5 -> 74160 | Y17: ='Data from MS project'!$E$127/5 -> 74160 | Z17: ='Data from MS project'!$E$127/5 -> 74160
A18: OP.60 | T18: ='Data from MS project'!$E$140/5 -> 74160 | U18: ='Data from MS project'!$E$140/5 -> 74160 | V18: ='Data from MS project'!$E$140/5 -> 74160 | W18: ='Data from MS project'!$E$140/5 -> 74160 | X18: ='Data from MS project'!$E$140/5 -> 74160
A19: OP.70 | T19: ='Data from MS project'!$E$145/3 -> 147000 | U19: ='Data from MS project'!$E$145/3 -> 147000 | V19: ='Data from MS project'!$E$145/3 -> 147000
A20: OP.80 | W20: ='Data from MS project'!$E$150/3 -> 147000 | X20: ='Data from MS project'!$E$150/3 -> 147000 | Y20: ='Data from MS project'!$E$150/3 -> 147000
A21: OP.90 | X21: ='Data from MS project'!$E$159/5 -> 74160 | Y21: ='Data from MS project'!$E$159/5 -> 74160 | Z21: ='Data from MS project'!$E$159/5 -> 74160 | AA21: ='Data from MS project'!$E$159/5 -> 74160 | AB21: ='Data from MS project'!$E$159/5 -> 74160
A22: OP.100 | Y22: ='Data from MS project'!$E$172/3 -> 147000 | Z22: ='Data from MS project'!$E$172/3 -> 147000 | AA22: ='Data from MS project'!$E$172/3 -> 147000
A23: OP.110 | X23: ='Data from MS project'!$E$177/5 -> 74160 | Y23: ='Data from MS project'!$E$177/5 -> 74160 | Z23: ='Data from MS project'!$E$177/5 -> 74160 | AA23: ='Data from MS project'!$E$177/5 -> 74160 | AB23: ='Data from MS project'!$E$177/5 -> 74160
A24: Final Line Testing | AB24: ='Data from MS project'!$E$182/3 -> 24533.333 | AC24: ='Data from MS project'!$E$182/3 -> 24533.333 | AD24: ='Data from MS project'!$E$182/3 -> 24533.333
A25: Contingency fund
A26: Total OPEX
A27: EBITD
A28: Depreciation
A29: EBIT
A30: Tax expense
A31: EBI(AT)
A32: CAPEX
A33: Engineering | B33: ='Data from MS project'!E3 -> 1342464
A34: Purchase process | J34: ='Data from MS project'!E16 -> 2800 | K34: ='Data from MS project'!E18 -> 2240
A35: Equipment and manufacturing | K35: =SUM('Data from MS project'!#REF!+'Data from MS project'!#REF!+'Data from MS project'!#REF!+'Data from MS project'!#REF!+'Data from MS project'!#REF!+'Data from MS project'!#REF!+'Data from MS project'!#REF!+ 'Data from MS project'!#REF!+'Data from MS project'!#REF!+'Data from MS project'!#REF!+'Data from MS project'!#REF!+'Data from MS project'!#REF!+'Data from MS project'!#REF!) -> #REF! | N35: =SUM('Data from MS project'!E50+'Data from MS project'!E47+'Data from MS project'!E38) -> 871300 | O35: ='Data from MS project'!E56 -> 480 | P35: =SUM('Data from MS project'!E32+'Data from MS project'!E35+'Data from MS project'!E53) -> 11000550 | Q35: =SUM('Data from MS project'!E65+'Data from MS project'!E62+'Data from MS project'!E59+'Data from MS project'!E44+'Data from MS project'!E41) -> 4401170
A36: Transportation | Q36: ='Data from MS project'!#REF!+'Data from MS project'!#REF!+'Data from MS project'!#REF!+'Data from MS project'!#REF!+'Data from MS project'!#REF!+'Data from MS project'!#REF!+'Data from MS project'!#REF!+'Data from MS project'!#REF!+'Data from MS project'!#REF! -> #REF! | S36: ='Data from MS project'!E70+'Data from MS project'!#REF!+'Data from MS project'!#REF! -> #REF!
A37: Total CAPEX | B37: =SUM(B33:B36) -> 1342464 | C37: =SUM(C33:C36) -> 0 | D37: =SUM(D33:D36) -> 0 | E37: =SUM(E33:E36) -> 0 | F37: =SUM(F33:F36) -> 0 | G37: =SUM(G33:G36) -> 0 | H37: =SUM(H33:H36) -> 0 | I37: =SUM(I33:I36) -> 0 | ... AD37: =SUM(AD33:AD36) -> 0
A38: Cash flow
A40: Cash Flow
A41: Cumulative Cash Flow
A42: DSCR
A43: Average
A44: Profitability
A45: Cost of equity
A46: NPV
A47: IRR
A50: Debt ratio
A51: Debt amount
A52: DSCR Rarget
... A61: NPV WACC

Sheet Cash flow
A1: Timeline | B1: 0 | C1: 1 | D1: 2 | E1: 3 | F1: 4 | G1: 5 | H1: 6 | I1: 7 | J1: 8 | K1: 9 | L1: 10 | M1: 11
A2: Year | B2: 2023 | C2: 2024 | D2: 2025 | E2: 2026 | F2: 2027 | G2: 2028 | H2: 2029 | I2: 2030 | J2: 2031 | K2: 2032 | L2: 2033 | M2: 2034
A3: Net cash flow
A4: INFLOWS
A5: Bank loan | C5: =B48 -> 10000000
A6: Sales revenue | C6: =(Revenues!$C$11) -> 0 | D6: =(Revenues!$D$11) -> 0 | E6: =(Revenues!$E$11) -> 7643490.2 | F6: =(Revenues!$F$11) -> 11924309 | G6: =(Revenues!$G$11) -> 16067155 | H6: =(Revenues!$H$11) -> 20580240 | I6: =(Revenues!$I$11) -> 25489563 | J6: =(Revenues!$J$11) -> 30822764 | K6: =(Revenues!$K$11) -> 36609224 | L6: =(Revenues!$L$11) -> 42880169 | M6: =(Revenues!$M$11) -> 49668776
A7: Government subsidies / incentives
A8: Joint venture funding
A9: Sum of INFLOWS | C9: =SUM(C5:C8) -> 10000000 | D9: =SUM(D6:D8) -> 0 | E9: =SUM(E6:E8) -> 7643490.2 | F9: =SUM(F6:F8) -> 11924309 | G9: =SUM(G6:G8) -> 16067155 | H9: =SUM(H6:H8) -> 20580240 | I9: =SUM(I6:I8) -> 25489563 | J9: =SUM(J6:J8) -> 30822764 | K9: =SUM(K6:K8) -> 36609224 | ... M9: =SUM(M6:M8) -> 49668776
A11: OUTFLOWS
A12: OPEX | G12: See sheet "Revenue" for information about the revenues
A13: Overhead costs | C13: ='Price Calculations, Assumptions'!$D$34*365 -> 2014732.2 | D13: ='Price Calculations, Assumptions'!$D$34*365 -> 2014732.2 | E13: ='Price Calculations, Assumptions'!$D$34*'Price Calculations, Assumptions'!L24 -> 877650.47 | G13: Please see below in the cash flow sheet (Wacc, NPV, debt amount, interests, equity to use etc.,)
A14: Production line setup costs | D14: ='Data from MS project'!E94-'Data from MS project'!E182 -> 4286000 | E14: ='Data from MS project'!E182 -> 73600
A15: ERP Implementation | D15: ='Data from MS project'!O4+'Data from MS project'!O6+'Data from MS project'!O12+'Data from MS project'!O17+'Data from MS project'!O24+'Data from MS project'!O30 -> 202904 | E15: ='Data from MS project'!O36+'Data from MS project'!O42 -> 33818
A16: Interests | E16: =IPMT($B$52,8,8,$B$48,0,0)*(-1) -> 65452.006 | F16: =IPMT($B$52,8,8,$B$48,0,0)*(-1) -> 65452.006 | G16: =IPMT($B$52,8,8,$B$48,0,0)*(-1) -> 65452.006 | H16: =IPMT($B$52,8,8,$B$48,0,0)*(-1) -> 65452.006 | I16: =IPMT($B$52,8,8,$B$48,0,0)*(-1) -> 65452.006 | J16: =IPMT($B$52,8,8,$B$48,0,0)*(-1) -> 65452.006 | K16: =IPMT($B$52,8,8,$B$48,0,0)*(-1) -> 65452.006 | L16: =IPMT($B$52,8,8,$B$48,0,0)*(-1) -> 65452.006 | M16: =IPMT($B$52,8,8,$B$48,0,0)*(-1) -> 65452.006
A17: Annual debt payment without interest | E17: =E18-E16 -> 1451264 | F17: =F18-F16 -> 1451264 | G17: =G18-G16 -> 1451264 | H17: =H18-H16 -> 1451264 | I17: =I18-I16 -> 1451264 | J17: =J18-J16 -> 1451264 | K17: =K18-K16 -> 1451264 | L17: =L18-L16 -> 1451264 | M17: =M18-M16 -> 1451264
A18: Total Annual debt payment | E18: =($B$56)*(-1) -> 1516716 | F18: =($B$56)*(-1) -> 1516716 | G18: =($B$56)*(-1) -> 1516716 | H18: =($B$56)*(-1) -> 1516716 | I18: =($B$56)*(-1) -> 1516716 | J18: =($B$56)*(-1) -> 1516716 | K18: =($B$56)*(-1) -> 1516716 | L18: =($B$56)*(-1) -> 1516716 | M18: =($B$56)*(-1) -> 1516716
A19: Total OPEX | C19: =SUM(C13:C18) -> 2014732.2 | D19: =SUM(D13:D18) -> 6503636.2 | E19: =SUM(E13:E18) -> 4018500.5 | F19: =SUM(F13:F18) -> 3033432 | G19: =SUM(G13:G18) -> 3033432 | H19: =SUM(H13:H18) -> 3033432 | I19: =SUM(I13:I18) -> 3033432 | J19: =SUM(J13:J18) -> 3033432 | ... M19: =SUM(M13:M18) -> 3033432
A21: EBITD | C21: =C9-C19 -> 7985267.8 | D21: =D9-D19 -> -6503636.2 | E21: =E9-E19 -> 3624989.7 | F21: =F9-F19 -> 8890877.1 | G21: =G9-G19 -> 13033723 | H21: =H9-H19 -> 17546808 | I21: =I9-I19 -> 22456131 | J21: =J9-J19 -> 27789332 | ... M21: =M9-M19 -> 46635344
A22: Depreciation | C22: 1307824 | D22: 1307824 | E22: 1307824 | F22: 1307824 | G22: 1307824 | H22: 1307824 | I22: 1307824 | J22: 1307824 | K22: 1307824 | L22: 1307824 | M22: 1307824
A23: EBIT | C23: =C21-C22 -> 6677443.8 | D23: =D21-D22 -> -7811460.2 | E23: =E21-E22 -> 2317165.7 | F23: =F21-F22 -> 7583053.1 | G23: =G21-G22 -> 11725899 | H23: =H21-H22 -> 16238984 | I23: =I21-I22 -> 21148307 | J23: =J21-J22 -> 26481508 | ... M23: =M21-M22 -> 45327520
A24: Tax expense | C24: =C23*'Price Calculations, Assumptions'!$J$10 -> 2270330.9 | D24: =D23*'Price Calculations, Assumptions'!$J$10 -> -2655896.5 | E24: =E23*'Price Calculations, Assumptions'!$J$10 -> 787836.35 | F24: =F23*'Price Calculations, Assumptions'!$J$10 -> 2578238.1 | G24: =G23*'Price Calculations, Assumptions'!$J$10 -> 3986805.6 | H24: =H23*'Price Calculations, Assumptions'!$J$10 -> 5521254.6 | I24: =I23*'Price Calculations, Assumptions'!$J$10 -> 7190424.3 | J24: =J23*'Price Calculations, Assumptions'!$J$10 -> 9003712.6 | ... M24: =M23*'Price Calculations, Assumptions'!$J$10 -> 15411357
A25: EBI(AT) | C25: =C23-C24 -> 4407112.9 | D25: =D23-D24 -> -5155563.7 | E25: =E23-E24 -> 1529329.4 | F25: =F23-F24 -> 5004815.1 | G25: =G23-G24 -> 7739093.2 | H25: =H23-H24 -> 10717730 | I25: =I23-I24 -> 13957883 | J25: =J23-J24 -> 17477795 | ... M25: =M23-M24 -> 29916163
A27: CAPEX
A28: Engineering | C28: ='Data from MS project'!E3 -> 1342464
A29: Purchase process | C29: ='Data from MS project'!E15 -> 5670
A30: Equipment manufacturing | C30: ='Data from MS project'!E29 -> 18686638
A31: Transportation | D31: 143000
A32: Contingency Fund | C32: 2619164.6
A34: Total CAPEX | C34: =SUM(C28:C32) -> 22653937 | D34: =SUM(D28:D32) -> 143000 | E34: =SUM(E28:E32) -> 0 | F34: =SUM(F28:F32) -> 0 | G34: =SUM(G28:G32) -> 0 | H34: =SUM(H28:H32) -> 0 | I34: =SUM(I28:I32) -> 0 | J34: =SUM(J28:J32) -> 0 | ... M34: =SUM(M28:M32) -> 0
A35: Net Cash Flow | C35: =C36+C22 -> -16939000 | D35: =D36+D22 -> -3990739.7 | E35: =E36+E22 -> 2837153.4 | F35: =F36+F22 -> 6312639.1 | G35: =G36+G22 -> 9046917.2 | H35: =H36+H22 -> 12025554 | I35: =I36+I22 -> 15265707 | J35: =J36+J22 -> 18785619 | ... M35: =M36+M22 -> 31223987
A36: Free Cash Flow | C36: =C25-C34 -> -18246824 | D36: =D25-D34 -> -5298563.7 | E36: =E25-E34 -> 1529329.4 | F36: =F25-F34 -> 5004815.1 | G36: =G25-G34 -> 7739093.2 | H36: =H25-H34 -> 10717730 | I36: =I25-I34 -> 13957883 | J36: =J25-J34 -> 17477795 | ... M36: =M25-M34 -> 29916163
A37: Cumulative Free Cash Flow | C37: =C36+D36 -> -23545387 | D37: =D36+E36 -> -3769234.3 | E37: =E36+F36 -> 6534144.5 | F37: =F36+G36 -> 12743908 | G37: =G36+H36 -> 18456823 | H37: =H36+I36 -> 24675612 | I37: =I36+J36 -> 31435678 | J37: =J36+K36 -> 38774654 | ... L37: =L36+M36 -> 55351846
A38: Net Cash Flow to repay the CAPEX | C38: =C35 -> -16939000 | D38: =D35*0.49 -> -1955462.5 | E38: =E35*0.49 -> 1390205.2 | F38: =F35*0.49 -> 3093193.1 | G38: =G35*0.49 -> 4432989.4 | H38: =H35*0.49 -> 5892521.2 | I38: =I35*0.49 -> 7480196.2 | J38: =J35*0.49 -> 9204953.3 | K38: =K35*0.49 -> 11076295 | ... M38: =M35*0.49 -> 15299754
A41: 1. Profitability without debt
A42: NPV | B42: =C35+NPV(B43,D38:M38) -> 11021391
A43: Cost of equity | B43: 0.13
A44: IRR | B44: =IRR(C35:M35) -> 0.34820479
A45: In this step NPV was computed just to show the advantages in terms of NPV if we use debt to finance the project
A47: 2. Choosing debt amount
A48: Amount of debt choosen | B48: 10000000
A49: Debt amount can range between 0 and the maximum amount of CAPEX
A50: DSCR target | B50: 1.7
A51: Total Capex | B51: =SUM(C34:D34) -> 22796937
A52: Cost of debt | B52: 0.0451
A53: First computation of the annual payment of debt | B53: =PMT(B52,10,B48,0) -> -1264409.7
A54: First Annual DSCR | C54: =-C38/$B$53 -> -13.396765 | D54: =-D38/$B$53 -> -1.5465418 | E54: =-E38/$B$53 -> 1.0994895 | F54: =-F38/$B$53 -> 2.4463536 | G54: =-G38/$B$53 -> 3.5059756 | H54: =-H38/$B$53 -> 4.6602943 | I54: =-I38/$B$53 -> 5.9159593 | J54: =-J38/$B$53 -> 7.2800403 | ... M54: =-M38/$B$53 -> 12.100314
A55: The first 2 years we can't meet the DSCR requirements, so as said during lecture is assumed that Magnus made a deal with the bank to start repaing the debt after 2 year
A56: New Annual Payment | B56: =PMT(B52,8,B48,0) -> -1516716
A57: New DSCR | E57: =-E38/$B$56 -> 0.91658897 | F57: =-F38/$B$56 -> 2.0394017 | G57: =-G38/$B$56 -> 2.9227551 | H57: =-H38/$B$56 -> 3.8850525 | I57: =-I38/$B$56 -> 4.9318371 | J57: =-J38/$B$56 -> 6.0690026 | K57: =-K38/$B$56 -> 7.3028138 | L57: =-L38/$B$56 -> 8.6399287 | M57: =-M38/$B$56 -> 10.087422
A58: In this step the debt to be contracted was first decided, then a DSCR target to be respected was set (usually the DSCR target must be greater than 1,5). Using the RATA (PMT in english) formula, the annual payment of debt was computed, but in this way there was a too low DSCR in the first two year.To solve this problem it was assumed that the company had an agreement with the bank to pay back the debt after 2 year, so when the factory is completed (to make this assumption realistic, a high cost of debt was chosen). So in this way a new annual payment of debt and new DSCRs were computed
A61: 3. Profitability with debt
A62: Equity to use = CAPEX - DEBT | B62: =B51-B48 -> 12796937
A63: Cost of equity of levered firm | B63: =B43+(B48/B62)*(B43-B52) -> 0.196344
A64: WACC | B64: =((B63*B62)/B51)+((B52*B48)/(B51)*(1-B65)) -> 0.12327366
A65: Tax rate | B65: 0.34
A66: NPV | B66: =C38+NPV(B64,D38:M38) -> 12245409

Sheet Cash Flow graph
B2: Year | C2: Net cash flow | D2: Free Cash Flow | E2: Net Cash Flow to repay the CAPEX | F2: Cumulative Net cash flow | G2: Cumulative free cash flow | H2: Cumulative Net Cash Flow to repay the CAPEX
B3: 2024 | C3: ='Cash flow'!C$35 -> -16939000 | D3: ='Cash flow'!C$36 -> -18246824 | E3: ='Cash flow'!C$38 -> -16939000 | F3: =C3/C14 -> -0.13669741 | G3: =D3/D14 -> -0.16659208 | H3: =E3/E14 -> -0.32524984
B4: 2025 | C4: ='Cash flow'!D$35 -> -3990739.7 | D4: ='Cash flow'!D$36 -> -5298563.7 | E4: ='Cash flow'!D$38 -> -1955462.5 | F4: =F3+(C4/$C$14) -> -0.1689026 | G4: =G3+(D4/$D$14) -> -0.21496755 | H4: =H3+(E4/$E$14) -> -0.36279715
B5: 2026 | C5: ='Cash flow'!E$35 -> 2837153.4 | D5: ='Cash flow'!E$36 -> 1529329.4 | E5: ='Cash flow'!E$38 -> 1390205.2 | F5: =F4+(C5/$C$14) -> -0.14600683 | G5: =G4+(D5/$D$14) -> -0.20100489 | H5: =H4+(E5/$E$14) -> -0.33610348
B6: 2027 | C6: ='Cash flow'!F$35 -> 6312639.1 | D6: ='Cash flow'!F$36 -> 5004815.1 | E6: ='Cash flow'!F$38 -> 3093193.1 | F6: =F5+(C6/$C$14) -> -0.095063951 | G6: =G5+(D6/$D$14) -> -0.15531132 | H6: =H5+(E6/$E$14) -> -0.27671033
B7: 2028 | C7: ='Cash flow'!G$35 -> 9046917.2 | D7: ='Cash flow'!G$36 -> 7739093.2 | E7: ='Cash flow'!G$38 -> 4432989.4 | F7: =F6+(C7/$C$14) -> -0.022055498 | G7: =G6+(D7/$D$14) -> -0.084654003 | H7: =H6+(E7/$E$14) -> -0.19159143
B8: 2029 | C8: ='Cash flow'!H$35 -> 12025554 | D8: ='Cash flow'!H$36 -> 10717730 | E8: ='Cash flow'!H$38 -> 5892521.2 | F8: =F7+(C8/$C$14) -> 0.074990492 | G8: =G7+(D8/$D$14) -> 0.013198031 | H8: =H7+(E8/$E$14) -> -0.078447698
B9: 2030 | C9: ='Cash flow'!I$35 -> 15265707 | D9: ='Cash flow'!I$36 -> 13957883 | E9: ='Cash flow'!I$38 -> 7480196.2 | F9: =F8+(C9/$C$14) -> 0.19818446 | G9: =G8+(D9/$D$14) -> 0.14063241 | H9: =H8+(E9/$E$14) -> 0.065181364
B10: 2031 | C10: ='Cash flow'!J$35 -> 18785619 | D10: ='Cash flow'!J$36 -> 17477795 | E10: ='Cash flow'!J$38 -> 9204953.3 | F10: =F9+(C10/$C$14) -> 0.34978405 | G10: =G9+(D10/$D$14) -> 0.30020331 | H10: =H9+(E10/$E$14) -> 0.24192791
B11: 2032 | C11: ='Cash flow'!K$35 -> 22604683 | D11: ='Cash flow'!K$36 -> 21296859 | E11: ='Cash flow'!K$38 -> 11076295 | F11: =F10+(C11/$C$14) -> 0.53220342 | G11: =G10+(D11/$D$14) -> 0.49464197 | H11: =H10+(E11/$E$14) -> 0.45460653
B12: 2033 | C12: ='Cash flow'!L$35 -> 26743506 | D12: ='Cash flow'!L$36 -> 25435682 | E12: ='Cash flow'!L$38 -> 13104318 | F12: =F11+(C12/$C$14) -> 0.74802301 | G12: =G11+(D12/$D$14) -> 0.72686776 | H12: =H11+(E12/$E$14) -> 0.70622572
B13: 2034 | C13: ='Cash flow'!M$35 -> 31223987 | D13: ='Cash flow'!M$36 -> 29916163 | E13: ='Cash flow'!M$38 -> 15299754 | F13: =F12+(C13/$C$14) -> 1 | G13: =G12+(D13/$D$14) -> 1 | H13: =H12+(E13/$E$14) -> 1
C14: =SUM(C3:C13) -> 1.2391603e+08 | D14: =SUM(D3:D13) -> 1.0952996e+08 | E14: =SUM(E3:E13) -> 52079963

Sheet Revenues
N1: 0.02
B2: 1 | C2: 2 | D2: 3 | E2: 4 | F2: 5 | G2: 6 | H2: 7 | I2: 8 | J2: 9 | K2: 10 | L2: 11 | M2: 12
B3: 2023 | C3: 2024 | D3: 2025 | E3: 2026 | F3: 2027 | G3: 2028 | H3: 2029 | I3: 2030 | J3: 2031 | K3: 2032 | L3: 2033 | M3: 2034
A4: Annual Total sales | B4: =$C$15*(1.048^B2) -> 3668000 | C4: =$C$15*(1.048^C2) -> 3844064 | D4: =$C$15*(1.048^D2) -> 4028579.1 | E4: =$C$15*(1.048^E2) -> 4221950.9 | F4: =$C$15*(1.048^F2) -> 4424604.5 | G4: =$C$15*(1.048^G2) -> 4636985.5 | H4: =$C$15*(1.048^H2) -> 4859560.8 | I4: =$C$15*(1.048^I2) -> 5092819.8 | ... M4: =$C$15*(1.048^M2) -> 6143324.2
A5: Annual sales on the aftermarket | B5: =0.1*B4 -> 366800 | C5: =0.1*C4 -> 384406.4 | D5: =0.1*D4 -> 402857.91 | E5: =0.1*E4 -> 422195.09 | F5: =0.1*F4 -> 442460.45 | G5: =0.1*G4 -> 463698.55 | H5: =0.1*H4 -> 485956.08 | I5: =0.1*I4 -> 509281.98 | ... M5: =0.1*M4 -> 614332.42
A6: Magnus share | B6: 0.05 | C6: 0 | D6: 0 | E6: =5% -> 0.05 | F6: =E6+2% -> 0.07 | G6: =F6+2% -> 0.09 | H6: =G6+2% -> 0.11 | I6: =H6+2% -> 0.13 | J6: =I6+2% -> 0.15 | K6: =J6+2% -> 0.17 | L6: =K6+2% -> 0.19 | M6: =L6+2% -> 0.21
A7: Piece sold by Magnus to Manufacturers | B7: =B6*B4 -> 183400 | C7: 0 | D7: 0 | E7: =E6*E4 -> 211097.54 | F7: =F6*F4 -> 309722.32 | G7: =G6*G4 -> 417328.7 | H7: =H6*H4 -> 534551.69 | I7: =I6*I4 -> 662066.57 | J7: =J6*J4 -> 800591.26 | K7: =K6*K4 -> 950888.93 | L7: =L6*L4 -> 1113770.6 | M7: =M6*M4 -> 1290098.1
A8: Piece sold by Magnus in the aftermarket | B8: =B6*B5 -> 18340 | C8: 0 | D8: 0 | E8: =E6*E5 -> 21109.754 | F8: =F6*F5 -> 30972.232 | G8: =G6*G5 -> 41732.87 | H8: =H6*H5 -> 53455.169 | I8: =I6*I5 -> 66206.657 | J8: =J6*J5 -> 80059.126 | K8: =K6*K5 -> 95088.893 | L8: =L6*L5 -> 111377.06 | M8: =M6*M5 -> 129009.81
A9: Sales | B9: =(B7+B8)*250*1000000 -> 50435000000000 | C9: =(C7+C8)*250 -> 0 | D9: =(D7+D8)*250 -> 0 | E9: =(E7+E8)*250 -> 58051824 | F9: =(F7+F8)*250 -> 85173637 | G9: =(G7+G8)*250 -> 1.1476539e+08 | H9: =(H7+H8)*250 -> 1.4700172e+08 | I9: =(I7+I8)*250 -> 1.8206831e+08 | J9: =(J7+J8)*250 -> 2.201626e+08 | ... M9: =(M7+M8)*250 -> 3.5477697e+08
A10: EBITDA/Sales | B10: =0.09 -> 0.09 | C10: 0 | D10: 0 | E10: =0.09*2/12+0.14*10/12 -> 0.13166667 | F10: 0.14 | G10: 0.14 | H10: 0.14 | I10: 0.14 | J10: 0.14 | K10: 0.14 | L10: 0.14 | M10: 0.14
A11: EBITDA from sales | B11: =B10*B9 -> 4539150000000 | C11: =C10*C9 -> 0 | D11: =D10*D9 -> 0 | E11: =E10*E9 -> 7643490.2 | F11: =F10*F9 -> 11924309 | G11: =G10*G9 -> 16067155 | H11: =H10*H9 -> 20580240 | I11: =I10*I9 -> 25489563 | ... M11: =M10*M9 -> 49668776
A12: EBITDA to repay the CAPEX | B12: =0.49*B11 -> 2224183500000 | C12: =0.49*C11 -> 0 | D12: =0.49*D11 -> 0 | E12: =0.49*E11 -> 3745310.2 | F12: =0.49*F11 -> 5842911.5 | G12: =0.49*G11 -> 7872905.9 | H12: =0.49*H11 -> 10084318 | I12: =0.49*I11 -> 12489886 | ... M12: =0.49*M11 -> 24337700
B13: Revenues computation must start from 2024
C14: Assumptions
C15: 3500000 | D15: Units sold in the market at the end of 2023
C16: Magnus has an initial market share of 5% and it increase of 2% every year
C17: Magnus has an initial aftermarket share of 5% and it increase of 2% every year
C18: The average price of the pieces sold by Magnus is 250€
C19: We start to sell when the indian factory is completed (17/02/26)
C20: Until project 3 is under realization, EBITDA/SALES=9%
C21: After completion of project 3 (23/06/26), EBITDA/SALES=14%
C22: The last row represent the earnings generated from selling the pieces on the market and aftermarket
